hotswap/__init__.py
hotswap/hotswap.py
hotcodeswap-1.0.1.dist-info/LICENSE
hotcodeswap-1.0.1.dist-info/METADATA
hotcodeswap-1.0.1.dist-info/WHEEL
hotcodeswap-1.0.1.dist-info/top_level.txt
hotcodeswap-1.0.1.dist-info/zip-safe
hotcodeswap-1.0.1.dist-info/RECORD
