Metadata-Version: 2.1
Name: hotcodeswap
Version: 1.0.1
Summary: Hot-swapper for Python
Home-page: https://github.com/nardpw/hotswap-for-python
Author: nardpw
Author-email: 
License: MIT
Classifier: Programming Language :: Python :: 3
License-File: LICENSE
